pyschlage/__init__.py
pyschlage/_version.py
pyschlage/api.py
pyschlage/auth.py
pyschlage/code.py
pyschlage/common.py
pyschlage/device.py
pyschlage/exceptions.py
pyschlage/lock.py
pyschlage/log.py
pyschlage/notification.py
pyschlage/py.typed
pyschlage/user.py
pyschlage-2025.9.0.dist-info/licenses/LICENSE
pyschlage-2025.9.0.dist-info/METADATA
pyschlage-2025.9.0.dist-info/WHEEL
pyschlage-2025.9.0.dist-info/top_level.txt
pyschlage-2025.9.0.dist-info/zip-safe
pyschlage-2025.9.0.dist-info/RECORD
