Metadata-Version: 2.4
Name: pyschlage
Version: 2025.9.0
Summary: Python API for interacting with Schlage WiFi locks.
Author-email: David Knowles <dknowles2@gmail.com>
License: Apache-2.0
Project-URL: Homepage, https://github.com/dknowles2/pyschlage
Project-URL: Source Code, https://github.com/dknowles2/pyschlage
Project-URL: Bug Reports, https://github.com/dknowles2/pyschlage/issues
Project-URL: Documentation, https://pyschlage.readthedocs.io
Keywords: schlage,api,iot
Platform: any
Classifier: Programming Language :: Python :: 3.11
Classifier: Programming Language :: Python :: 3.12
Classifier: Topic :: Software Development :: Libraries :: Python Modules
Requires-Python: >=3.11
License-File: LICENSE
Requires-Dist: pycognito
Requires-Dist: requests
Dynamic: license-file
